Workbook

Sheet Painel & Instruções
B2: SISTEMA INTEGRADO DE ESTOQUE & CURVA ABC PARA MARKETPLACES
B4: Ferramenta Oficial Complementar ao Precificador Pro • Mercado Livre, Shopee, Amazon, Shein e Magalu
B6: TOTAL EM ESTOQUE (UNID) | D6: VALOR TOTAL INVESTIDO | F6: ITENS PARA REPOR | H6: ITENS ZERADOS (RUPTURA)
B7: =SOMA('Controle de Estoque'!F7:F26) | D7: =SOMA('Controle de Estoque'!I7:I26) | F7: =CONT.SE('Controle de Estoque'!J7:J26, "*REPOR*") | H7: =CONT.SE('Controle de Estoque'!J7:J26, "*ZERADO*")
B9: COMO UTILIZAR ESTA PLANILHA
B11: 1. Aba "Controle de Estoque": | C11: Cadastre seus produtos com Estoque Atual, Estoque Mínimo e Custo Unitário. A coluna Status avisa em verde, amarelo ou vermelho automaticamente quando você precisa repor.
B13: 2. Aba "Curva ABC de Vendas": | C13: Insira o volume de vendas e preço médio de cada produto. A planilha calcula sozinha a fatia de faturamento de cada item e classifica em A (80% do seu lucro), B (15%) e C (5%).
B15: 3. Aba "Giro & Cobertura": | C15: Descubra exatamente quantos dias de estoque você ainda tem antes de zerar, permitindo negociar com fornecedores com antecedência sem pagar frete aéreo ou perder vendas.
B17: 4. Sincronização com Precificador Pro: | C17: Use os mesmos custos unitários e preços de venda calculados no seu aplicativo Precificador Pro para garantir margens sempre consistentes e blindadas contra prejuízo.
B20: GUIA ESTRATÉGICO DA CURVA ABC DE PARETO
B22: Classificação | D22: Impacto no Faturamento | F22: Estratégia Recomendada para o Seller
B23: CLASSE A (Top 20% dos Produtos) | D23: Representam cerca de 80% do seu faturamento. | F23: NUNCA deixe faltar em estoque. Negocie prazo e preço agressivo com fornecedor. Ative Full / FBA.
B24: CLASSE B (30% dos Produtos) | D24: Representam cerca de 15% do seu faturamento. | F24: Estoque de giro regular. Mantenha ponto de reposição padrão de 15 a 30 dias.
B25: CLASSE C (50% dos Produtos) | D25: Representam apenas 5% do faturamento total. | F25: Cuidado com capital parado! Faça promoções, queima de estoque ou monte Kits/Combos no Precificador Pro para desovar.

Sheet Controle de Estoque
A2: CONTROLE E GESTÃO DE ESTOQUE POR SKU & MARKETPLACE
A5: Código SKU | B5: Descrição do Produto | C5: Categoria | D5: Canal Principal | E5: Estoque Mínimo | F5: Estoque Atual | G5: Ponto Reposição | H5: Custo Unit. (R$) | I5: Valor Total Estoque (R$) | J5: Status de Reposição
A7: FONE-BT-01 | B7: Fone de Ouvido Bluetooth TWS Pro | C7: Eletrônicos | D7: Mercado Livre | E7: 20 | F7: 85 | G7: 35 | H7: 32 | I7: =F7*H7 | J7: =IF(F7<=0, "🔴 ZERADO", IF(F7<=G7, "🟡 REPOR URGENTE", "🟢 NORMAL"))
A8: GARRAFA-500 | B8: Garrafa Térmica Inox 500ml Digital | C8: Casa & Cozinha | D8: Shopee | E8: 15 | F8: 62 | G8: 25 | H8: 18.5 | I8: =F8*H8 | J8: =IF(F8<=0, "🔴 ZERADO", IF(F8<=G8, "🟡 REPOR URGENTE", "🟢 NORMAL"))
A9: CABO-USBC-2M | B9: Cabo USB-C Trançado Nylon 2m Turbo | C9: Acessórios | D9: Shopee | E9: 30 | F9: 140 | G9: 50 | H9: 6.2 | I9: =F9*H9 | J9: =IF(F9<=0, "🔴 ZERADO", IF(F9<=G9, "🟡 REPOR URGENTE", "🟢 NORMAL"))
A10: SUPORTE-NOTE | B10: Suporte Articulado para Notebook Ergonômico | C10: Informática | D10: Amazon | E10: 10 | F10: 8 | G10: 15 | H10: 28 | I10: =F10*H10 | J10: =IF(F10<=0, "🔴 ZERADO", IF(F10<=G10, "🟡 REPOR URGENTE", "🟢 NORMAL"))
A11: RING-LIGHT-10 | B11: Ring Light 10 Pol Tripé 2m + Controle | C11: Fotografia | D11: Mercado Livre | E11: 15 | F11: 0 | G11: 20 | H11: 34 | I11: =F11*H11 | J11: =IF(F11<=0, "🔴 ZERADO", IF(F11<=G11, "🟡 REPOR URGENTE", "🟢 NORMAL"))
A12: KIT-MEIAS-12 | B12: Kit 12 Pares de Meia Algodão Cano Curto | C12: Moda | D12: Shopee | E12: 40 | F12: 95 | G12: 60 | H12: 14 | I12: =F12*H12 | J12: =IF(F12<=0, "🔴 ZERADO", IF(F12<=G12, "🟡 REPOR URGENTE", "🟢 NORMAL"))
A13: CARREGADOR-20W | B13: Carregador Rápido 20W USB-C Homologado | C13: Eletrônicos | D13: Mercado Livre | E13: 25 | F13: 18 | G13: 35 | H13: 19.5 | I13: =F13*H13 | J13: =IF(F13<=0, "🔴 ZERADO", IF(F13<=G13, "🟡 REPOR URGENTE", "🟢 NORMAL"))
A14: LUMINARIA-MESA | B14: Luminária de Mesa LED Articulada Touch | C14: Casa & Cozinha | D14: Shein | E14: 15 | F14: 32 | G14: 25 | H14: 22 | I14: =F14*H14 | J14: =IF(F14<=0, "🔴 ZERADO", IF(F14<=G14, "🟡 REPOR URGENTE", "🟢 NORMAL"))
A15: CAPA-IPHONE-15 | B15: Capa Magnética Silicone Anti-Impacto | C15: Acessórios | D15: Shopee | E15: 50 | F15: 110 | G15: 75 | H15: 5.8 | I15: =F15*H15 | J15: =IF(F15<=0, "🔴 ZERADO", IF(F15<=G15, "🟡 REPOR URGENTE", "🟢 NORMAL"))
A16: MOCKUP-ORGANIZ | B16: Organizador de Cabos e Fones Portátil | C16: Utilidades | D16: TikTok Shop | E16: 20 | F16: 45 | G16: 30 | H16: 4.5 | I16: =F16*H16 | J16: =IF(F16<=0, "🔴 ZERADO", IF(F16<=G16, "🟡 REPOR URGENTE", "🟢 NORMAL"))
A17: TECLADO-MEC-RGB | B17: Teclado Mecânico Compacto RGB ABNT2 | C17: Informática | D17: Amazon | E17: 10 | F17: 5 | G17: 15 | H17: 75 | I17: =F17*H17 | J17: =IF(F17<=0, "🔴 ZERADO", IF(F17<=G17, "🟡 REPOR URGENTE", "🟢 NORMAL"))
A18: MOUSE-SEM-FIO | B18: Mouse Óptico Recarregável Silencioso 2.4G | C18: Informática | D18: Mercado Livre | E18: 20 | F18: 55 | G18: 30 | H18: 16 | I18: =F18*H18 | J18: =IF(F18<=0, "🔴 ZERADO", IF(F18<=G18, "🟡 REPOR URGENTE", "🟢 NORMAL"))
... A26: ALMOFADA-MASSAGEM | B26: Almofada de Massagem Shiatsu Pescoço e Lombar | C26: Saúde & Bem-Estar | D26: Mercado Livre | E26: 10 | F26: 19 | G26: 15 | H26: 42 | I26: =F26*H26 | J26: =IF(F26<=0, "🔴 ZERADO", IF(F26<=G26, "🟡 REPOR URGENTE", "🟢 NORMAL"))
B27: TOTAL GERAL | F27: =SUM(F7:F26) | I27: =SUM(I7:I26)

Sheet Curva ABC
A2: MATRIZ CURVA ABC DE VENDAS (REGRA DE PARETO 80/20)
A5: Ranking | B5: Código SKU | C5: Descrição do Produto | D5: Canal Principal | E5: Vendas Mensais (Qtd) | F5: Preço Médio Venda (R$) | G5: Faturamento Total (R$) | H5: % Faturamento | I5: % Acumulado | J5: Classe ABC
A7: 1 | B7: FONE-BT-01 | C7: Fone de Ouvido Bluetooth TWS Pro | D7: Mercado Livre | E7: 260 | F7: 89.9 | G7: =E7*F7 | H7: =G7/$G$27 | I7: =H7 | J7: =IF(I7<=0.80, "CLASSE A (Ouro)", IF(I7<=0.95, "CLASSE B (Prata)", "CLASSE C (Bronze)"))
A8: 2 | B8: ESCOVA-SECADORA | C8: Escova Secadora Modeladora Oval 1200W | D8: Magalu | E8: 140 | F8: 139.9 | G8: =E8*F8 | H8: =G8/$G$27 | I8: =I7+H8 | J8: =IF(I8<=0.80, "CLASSE A (Ouro)", IF(I8<=0.95, "CLASSE B (Prata)", "CLASSE C (Bronze)"))
A9: 3 | B9: TECLADO-MEC-RGB | C9: Teclado Mecânico Compacto RGB ABNT2 | D9: Amazon | E9: 90 | F9: 189.9 | G9: =E9*F9 | H9: =G9/$G$27 | I9: =I8+H9 | J9: =IF(I9<=0.80, "CLASSE A (Ouro)", IF(I9<=0.95, "CLASSE B (Prata)", "CLASSE C (Bronze)"))
A10: 4 | B10: GARRAFA-500 | C10: Garrafa Térmica Inox 500ml Digital | D10: Shopee | E10: 280 | F10: 49.9 | G10: =E10*F10 | H10: =G10/$G$27 | I10: =I9+H10 | J10: =IF(I10<=0.80, "CLASSE A (Ouro)", IF(I10<=0.95, "CLASSE B (Prata)", "CLASSE C (Bronze)"))
A11: 5 | B11: MOCHILA-ANTIFURTO | C11: Mochila Impermeável para Notebook com USB | D11: Mercado Livre | E11: 110 | F11: 119.9 | G11: =E11*F11 | H11: =G11/$G$27 | I11: =I10+H11 | J11: =IF(I11<=0.80, "CLASSE A (Ouro)", IF(I11<=0.95, "CLASSE B (Prata)", "CLASSE C (Bronze)"))
A12: 6 | B12: RELOGIO-SMART-D20 | C12: Smartwatch D20 Bluetooth Monitor Saúde | D12: Shopee | E12: 240 | F12: 45.9 | G12: =E12*F12 | H12: =G12/$G$27 | I12: =I11+H12 | J12: =IF(I12<=0.80, "CLASSE A (Ouro)", IF(I12<=0.95, "CLASSE B (Prata)", "CLASSE C (Bronze)"))
A13: 7 | B13: CARREGADOR-20W | C13: Carregador Rápido 20W USB-C Homologado | D13: Mercado Livre | E13: 190 | F13: 54.9 | G13: =E13*F13 | H13: =G13/$G$27 | I13: =I12+H13 | J13: =IF(I13<=0.80, "CLASSE A (Ouro)", IF(I13<=0.95, "CLASSE B (Prata)", "CLASSE C (Bronze)"))
A14: 8 | B14: ALMOFADA-MASSAGEM | C14: Almofada de Massagem Shiatsu Pescoço e Lombar | D14: Mercado Livre | E14: 80 | F14: 119.9 | G14: =E14*F14 | H14: =G14/$G$27 | I14: =I13+H14 | J14: =IF(I14<=0.80, "CLASSE A (Ouro)", IF(I14<=0.95, "CLASSE B (Prata)", "CLASSE C (Bronze)"))
A15: 9 | B15: SUPORTE-NOTE | C15: Suporte Articulado para Notebook Ergonômico | D15: Amazon | E15: 120 | F15: 69.9 | G15: =E15*F15 | H15: =G15/$G$27 | I15: =I14+H15 | J15: =IF(I15<=0.80, "CLASSE A (Ouro)", IF(I15<=0.95, "CLASSE B (Prata)", "CLASSE C (Bronze)"))
A16: 10 | B16: CAIXA-SOM-BT | C16: Mini Caixa de Som Bluetooth À Prova D'Água | D16: Mercado Livre | E16: 95 | F16: 79.9 | G16: =E16*F16 | H16: =G16/$G$27 | I16: =I15+H16 | J16: =IF(I16<=0.80, "CLASSE A (Ouro)", IF(I16<=0.95, "CLASSE B (Prata)", "CLASSE C (Bronze)"))
A17: 11 | B17: RING-LIGHT-10 | C17: Ring Light 10 Pol Tripé 2m + Controle | D17: Mercado Livre | E17: 85 | F17: 79.9 | G17: =E17*F17 | H17: =G17/$G$27 | I17: =I16+H17 | J17: =IF(I17<=0.80, "CLASSE A (Ouro)", IF(I17<=0.95, "CLASSE B (Prata)", "CLASSE C (Bronze)"))
A18: 12 | B18: LUMINARIA-MESA | C18: Luminária de Mesa LED Articulada Touch | D18: Shein | E18: 110 | F18: 59.9 | G18: =E18*F18 | H18: =G18/$G$27 | I18: =I17+H18 | J18: =IF(I18<=0.80, "CLASSE A (Ouro)", IF(I18<=0.95, "CLASSE B (Prata)", "CLASSE C (Bronze)"))
A19: 13 | B19: MOUSE-SEM-FIO | C19: Mouse Óptico Recarregável Silencioso 2.4G | D19: Mercado Livre | E19: 130 | F19: 42.9 | G19: =E19*F19 | H19: =G19/$G$27 | I19: =I18+H19 | J19: =IF(I19<=0.80, "CLASSE A (Ouro)", IF(I19<=0.95, "CLASSE B (Prata)", "CLASSE C (Bronze)"))
... A26: 20 | B26: MOCKUP-ORGANIZ | C26: Organizador de Cabos e Fones Portátil | D26: TikTok Shop | E26: 90 | F26: 16.9 | G26: =E26*F26 | H26: =G26/$G$27 | I26: =I25+H26 | J26: =IF(I26<=0.80, "CLASSE A (Ouro)", IF(I26<=0.95, "CLASSE B (Prata)", "CLASSE C (Bronze)"))
C27: FATURAMENTO TOTAL | E27: =SUM(E7:E26) | G27: =SUM(G7:G26) | H27: =SUM(H7:H26)

Sheet Giro & Cobertura
A2: DIAS DE COBERTURA DE ESTOQUE & PREVISÃO DE RUPTURA
A5: Código SKU | B5: Descrição do Produto | C5: Estoque Atual (Unid) | D5: Venda Média / Dia | E5: Dias de Cobertura Restantes | F5: Nível de Risco | G5: Previsão de Ruptura | H5: Ação Imediata Recomendada
A7: FONE-BT-01 | B7: Fone de Ouvido Bluetooth TWS Pro | C7: 85 | D7: =ROUND('Curva ABC'!E7/30, 1) | E7: =IF(D7>0, ROUND(C7/D7, 0), 999) | F7: =IF(C7<=0, "CRÍTICO (ZERADO)", IF(E7<=15, "ALTO RISCO", IF(E7<=30, "MODERADO", "CONFORTÁVEL"))) | G7: =IF(C7<=0, "HOJE", TODAY() + E7) | H7: =IF(C7<=0, "Emitir Pedido Urgente para Fornecedor", IF(E7<=15, "Repor lote de segurança imediatamente", IF(E7<=30, "Acompanhar giro na próxima semana", "Estoque suficiente para o ciclo")))
A8: GARRAFA-500 | B8: Garrafa Térmica Inox 500ml Digital | C8: 62 | D8: =ROUND('Curva ABC'!E8/30, 1) | E8: =IF(D8>0, ROUND(C8/D8, 0), 999) | F8: =IF(C8<=0, "CRÍTICO (ZERADO)", IF(E8<=15, "ALTO RISCO", IF(E8<=30, "MODERADO", "CONFORTÁVEL"))) | G8: =IF(C8<=0, "HOJE", TODAY() + E8) | H8: =IF(C8<=0, "Emitir Pedido Urgente para Fornecedor", IF(E8<=15, "Repor lote de segurança imediatamente", IF(E8<=30, "Acompanhar giro na próxima semana", "Estoque suficiente para o ciclo")))
A9: CABO-USBC-2M | B9: Cabo USB-C Trançado Nylon 2m Turbo | C9: 140 | D9: =ROUND('Curva ABC'!E9/30, 1) | E9: =IF(D9>0, ROUND(C9/D9, 0), 999) | F9: =IF(C9<=0, "CRÍTICO (ZERADO)", IF(E9<=15, "ALTO RISCO", IF(E9<=30, "MODERADO", "CONFORTÁVEL"))) | G9: =IF(C9<=0, "HOJE", TODAY() + E9) | H9: =IF(C9<=0, "Emitir Pedido Urgente para Fornecedor", IF(E9<=15, "Repor lote de segurança imediatamente", IF(E9<=30, "Acompanhar giro na próxima semana", "Estoque suficiente para o ciclo")))
A10: SUPORTE-NOTE | B10: Suporte Articulado para Notebook Ergonômico | C10: 8 | D10: =ROUND('Curva ABC'!E10/30, 1) | E10: =IF(D10>0, ROUND(C10/D10, 0), 999) | F10: =IF(C10<=0, "CRÍTICO (ZERADO)", IF(E10<=15, "ALTO RISCO", IF(E10<=30, "MODERADO", "CONFORTÁVEL"))) | G10: =IF(C10<=0, "HOJE", TODAY() + E10) | H10: =IF(C10<=0, "Emitir Pedido Urgente para Fornecedor", IF(E10<=15, "Repor lote de segurança imediatamente", IF(E10<=30, "Acompanhar giro na próxima semana", "Estoque suficiente para o ciclo")))
A11: RING-LIGHT-10 | B11: Ring Light 10 Pol Tripé 2m + Controle | C11: 0 | D11: =ROUND('Curva ABC'!E11/30, 1) | E11: =IF(D11>0, ROUND(C11/D11, 0), 999) | F11: =IF(C11<=0, "CRÍTICO (ZERADO)", IF(E11<=15, "ALTO RISCO", IF(E11<=30, "MODERADO", "CONFORTÁVEL"))) | G11: =IF(C11<=0, "HOJE", TODAY() + E11) | H11: =IF(C11<=0, "Emitir Pedido Urgente para Fornecedor", IF(E11<=15, "Repor lote de segurança imediatamente", IF(E11<=30, "Acompanhar giro na próxima semana", "Estoque suficiente para o ciclo")))
A12: KIT-MEIAS-12 | B12: Kit 12 Pares de Meia Algodão Cano Curto | C12: 95 | D12: =ROUND('Curva ABC'!E12/30, 1) | E12: =IF(D12>0, ROUND(C12/D12, 0), 999) | F12: =IF(C12<=0, "CRÍTICO (ZERADO)", IF(E12<=15, "ALTO RISCO", IF(E12<=30, "MODERADO", "CONFORTÁVEL"))) | G12: =IF(C12<=0, "HOJE", TODAY() + E12) | H12: =IF(C12<=0, "Emitir Pedido Urgente para Fornecedor", IF(E12<=15, "Repor lote de segurança imediatamente", IF(E12<=30, "Acompanhar giro na próxima semana", "Estoque suficiente para o ciclo")))
A13: CARREGADOR-20W | B13: Carregador Rápido 20W USB-C Homologado | C13: 18 | D13: =ROUND('Curva ABC'!E13/30, 1) | E13: =IF(D13>0, ROUND(C13/D13, 0), 999) | F13: =IF(C13<=0, "CRÍTICO (ZERADO)", IF(E13<=15, "ALTO RISCO", IF(E13<=30, "MODERADO", "CONFORTÁVEL"))) | G13: =IF(C13<=0, "HOJE", TODAY() + E13) | H13: =IF(C13<=0, "Emitir Pedido Urgente para Fornecedor", IF(E13<=15, "Repor lote de segurança imediatamente", IF(E13<=30, "Acompanhar giro na próxima semana", "Estoque suficiente para o ciclo")))
A14: LUMINARIA-MESA | B14: Luminária de Mesa LED Articulada Touch | C14: 32 | D14: =ROUND('Curva ABC'!E14/30, 1) | E14: =IF(D14>0, ROUND(C14/D14, 0), 999) | F14: =IF(C14<=0, "CRÍTICO (ZERADO)", IF(E14<=15, "ALTO RISCO", IF(E14<=30, "MODERADO", "CONFORTÁVEL"))) | G14: =IF(C14<=0, "HOJE", TODAY() + E14) | H14: =IF(C14<=0, "Emitir Pedido Urgente para Fornecedor", IF(E14<=15, "Repor lote de segurança imediatamente", IF(E14<=30, "Acompanhar giro na próxima semana", "Estoque suficiente para o ciclo")))
A15: CAPA-IPHONE-15 | B15: Capa Magnética Silicone Anti-Impacto | C15: 110 | D15: =ROUND('Curva ABC'!E15/30, 1) | E15: =IF(D15>0, ROUND(C15/D15, 0), 999) | F15: =IF(C15<=0, "CRÍTICO (ZERADO)", IF(E15<=15, "ALTO RISCO", IF(E15<=30, "MODERADO", "CONFORTÁVEL"))) | G15: =IF(C15<=0, "HOJE", TODAY() + E15) | H15: =IF(C15<=0, "Emitir Pedido Urgente para Fornecedor", IF(E15<=15, "Repor lote de segurança imediatamente", IF(E15<=30, "Acompanhar giro na próxima semana", "Estoque suficiente para o ciclo")))
A16: MOCKUP-ORGANIZ | B16: Organizador de Cabos e Fones Portátil | C16: 45 | D16: =ROUND('Curva ABC'!E16/30, 1) | E16: =IF(D16>0, ROUND(C16/D16, 0), 999) | F16: =IF(C16<=0, "CRÍTICO (ZERADO)", IF(E16<=15, "ALTO RISCO", IF(E16<=30, "MODERADO", "CONFORTÁVEL"))) | G16: =IF(C16<=0, "HOJE", TODAY() + E16) | H16: =IF(C16<=0, "Emitir Pedido Urgente para Fornecedor", IF(E16<=15, "Repor lote de segurança imediatamente", IF(E16<=30, "Acompanhar giro na próxima semana", "Estoque suficiente para o ciclo")))
A17: TECLADO-MEC-RGB | B17: Teclado Mecânico Compacto RGB ABNT2 | C17: 5 | D17: =ROUND('Curva ABC'!E17/30, 1) | E17: =IF(D17>0, ROUND(C17/D17, 0), 999) | F17: =IF(C17<=0, "CRÍTICO (ZERADO)", IF(E17<=15, "ALTO RISCO", IF(E17<=30, "MODERADO", "CONFORTÁVEL"))) | G17: =IF(C17<=0, "HOJE", TODAY() + E17) | H17: =IF(C17<=0, "Emitir Pedido Urgente para Fornecedor", IF(E17<=15, "Repor lote de segurança imediatamente", IF(E17<=30, "Acompanhar giro na próxima semana", "Estoque suficiente para o ciclo")))
A18: MOUSE-SEM-FIO | B18: Mouse Óptico Recarregável Silencioso 2.4G | C18: 55 | D18: =ROUND('Curva ABC'!E18/30, 1) | E18: =IF(D18>0, ROUND(C18/D18, 0), 999) | F18: =IF(C18<=0, "CRÍTICO (ZERADO)", IF(E18<=15, "ALTO RISCO", IF(E18<=30, "MODERADO", "CONFORTÁVEL"))) | G18: =IF(C18<=0, "HOJE", TODAY() + E18) | H18: =IF(C18<=0, "Emitir Pedido Urgente para Fornecedor", IF(E18<=15, "Repor lote de segurança imediatamente", IF(E18<=30, "Acompanhar giro na próxima semana", "Estoque suficiente para o ciclo")))
... A26: ALMOFADA-MASSAGEM | B26: Almofada de Massagem Shiatsu Pescoço e Lombar | C26: 19 | D26: =ROUND('Curva ABC'!E26/30, 1) | E26: =IF(D26>0, ROUND(C26/D26, 0), 999) | F26: =IF(C26<=0, "CRÍTICO (ZERADO)", IF(E26<=15, "ALTO RISCO", IF(E26<=30, "MODERADO", "CONFORTÁVEL"))) | G26: =IF(C26<=0, "HOJE", TODAY() + E26) | H26: =IF(C26<=0, "Emitir Pedido Urgente para Fornecedor", IF(E26<=15, "Repor lote de segurança imediatamente", IF(E26<=30, "Acompanhar giro na próxima semana", "Estoque suficiente para o ciclo")))
